phovea_data_mongo/__init__.py
phovea_data_mongo/config.json
phovea_data_mongo/graph.py
phovea_data_mongo-8.0.0.dist-info/LICENSE
phovea_data_mongo-8.0.0.dist-info/METADATA
phovea_data_mongo-8.0.0.dist-info/WHEEL
phovea_data_mongo-8.0.0.dist-info/entry_points.txt
phovea_data_mongo-8.0.0.dist-info/top_level.txt
phovea_data_mongo-8.0.0.dist-info/RECORD
