Metadata-Version: 2.1
Name: phovea-data-mongo
Version: 8.0.0
Summary: DEPRECATED: Data provider plugin for loading graph data stored in a MongoDB.
Home-page: https://phovea.caleydo.org
Author: The Caleydo Team
Author-email: contact@caleydo.org
License: BSD-3-Clause
Platform: UNKNOWN
Classifier: Intended Audience :: Developers
Classifier: Operating System :: OS Independent
Classifier: License :: OSI Approved :: BSD License
Classifier: Programming Language :: Python
Classifier: Programming Language :: Python :: 3.7
License-File: LICENSE
Requires-Dist: pymongo (~=3.11.1)
Requires-Dist: phovea-server (<8.0.0,>=7.2.0)
